LICENSE
MANIFEST.in
README.rst
buildout.cfg
develop.cfg
requirements.txt
setup.py
version.txt
bob/__init__.py
bob.ip.optflow.hornschunck.egg-info/PKG-INFO
bob.ip.optflow.hornschunck.egg-info/SOURCES.txt
bob.ip.optflow.hornschunck.egg-info/dependency_links.txt
bob.ip.optflow.hornschunck.egg-info/not-zip-safe
bob.ip.optflow.hornschunck.egg-info/requires.txt
bob.ip.optflow.hornschunck.egg-info/top_level.txt
bob/ip/__init__.py
bob/ip/optflow/__init__.py
bob/ip/optflow/hornschunck/HornAndSchunckFlow.cpp
bob/ip/optflow/hornschunck/HornAndSchunckFlow.h
bob/ip/optflow/hornschunck/SpatioTemporalGradient.cpp
bob/ip/optflow/hornschunck/SpatioTemporalGradient.h
bob/ip/optflow/hornschunck/__init__.py
bob/ip/optflow/hornschunck/central.cpp
bob/ip/optflow/hornschunck/flow.cpp
bob/ip/optflow/hornschunck/forward.cpp
bob/ip/optflow/hornschunck/main.cpp
bob/ip/optflow/hornschunck/test_flow.py
bob/ip/optflow/hornschunck/test_gradient.py
bob/ip/optflow/hornschunck/utils.py
bob/ip/optflow/hornschunck/vanilla.cpp
bob/ip/optflow/hornschunck/version.cpp
bob/ip/optflow/hornschunck/example/__init__.py
bob/ip/optflow/hornschunck/example/optflow_hs.py
doc/conf.py
doc/guide.rst
doc/index.rst
doc/links.rst
doc/py_api.rst